molecularnetwork/__init__.py
molecularnetwork/featurizer.py
molecularnetwork/graph.py
molecularnetwork/similarity.py
molecularnetwork/utils.py
molecularnetwork-0.4.6.dist-info/LICENSE
molecularnetwork-0.4.6.dist-info/METADATA
molecularnetwork-0.4.6.dist-info/WHEEL
molecularnetwork-0.4.6.dist-info/RECORD
