Metadata-Version: 2.1
Name: molecularnetwork
Version: 0.4.6
Summary: Helper Library to create Molecular Networks
License: MIT
Author: Manas Mahale
Author-email: manas.mahale@bcp.edu.in
Requires-Python: >=3.9,<4.0
Classifier: License :: OSI Approved :: MIT License
Classifier: Programming Language :: Python :: 3
Classifier: Programming Language :: Python :: 3.9
Classifier: Programming Language :: Python :: 3.10
Classifier: Programming Language :: Python :: 3.11
Classifier: Programming Language :: Python :: 3.12
